wizconfig/__init__.py
wizconfig-1.0.2.dist-info/LICENSE
wizconfig-1.0.2.dist-info/METADATA
wizconfig-1.0.2.dist-info/WHEEL
wizconfig-1.0.2.dist-info/top_level.txt
wizconfig-1.0.2.dist-info/RECORD
