Metadata-Version: 2.1
Name: wizconfig
Version: 1.0.2
Summary: An incomplete configuration shall not pass.
Author-email: Matthias Reumann <matthias.reumann@tum.de>
License: MIT
Project-URL: Homepage, https://github.com/ACONIO/wizconfig
Keywords: python,configuration,environment
Requires-Python: >=3.7
License-File: LICENSE
